ts_ids_core/__init__.py
ts_ids_core/_internal.py
ts_ids_core/annotations.py
ts_ids_core/base/__init__.py
ts_ids_core/base/ids_element.py
ts_ids_core/base/ids_field.py
ts_ids_core/base/ids_undefined_type.py
ts_ids_core/base/meta.py
ts_ids_core/errors.py
ts_ids_core/py.typed
ts_ids_core/schema/__init__.py
ts_ids_core/schema/datacube.py
ts_ids_core/schema/dimension.py
ts_ids_core/schema/ids_schema.py
ts_ids_core/schema/measure.py
ts_ids_core/schema/modifier.py
ts_ids_core/schema/parameter.py
ts_ids_core/schema/project.py
ts_ids_core/schema/related_file.py
ts_ids_core/schema/run.py
ts_ids_core/schema/sample.py
ts_ids_core/schema/system.py
ts_ids_core/schema/time_.py
ts_ids_core/schema/user.py
ts_ids_core/schema/value_unit.py
ts_ids_core/scripts/__init__.py
ts_ids_core/scripts/_logging.py
ts_ids_core/scripts/_templates/pydantic_v2/BaseModel.jinja2
ts_ids_core/scripts/cli.py
ts_ids_core/scripts/docs.py
ts_ids_core/scripts/jsonschema_to_programmatic_ids.py
ts_ids_core/scripts/programmatic_ids_to_jsonschema.py
ts_ids_core-2.0.0.dist-info/METADATA
ts_ids_core-2.0.0.dist-info/WHEEL
ts_ids_core-2.0.0.dist-info/entry_points.txt
ts_ids_core-2.0.0.dist-info/licenses/LICENSE
ts_ids_core-2.0.0.dist-info/RECORD
